{"key":"7FAB1CED6D","component":"Form","name":"Form","type":"form","conditions":[],"items":[{"key":"46BDCACC2F4D5ED","reportItemKey":"46BDCACC2F4D5ED","name":"Front Page","type":"page","conditions":[],"component":"Page","reportComponent":"Page","canRemove":true,"items":[{"key":"990822FE443C6D7","reportItemKey":"990822FE443C6D7","name":"Row","type":"row","conditions":[],"component":"Row","reportComponent":"Row","canRemove":true,"items":[{"key":"99705E1BD0831D5","reportItemKey":"99705E1BD0831D5","name":"Items holder","type":"column","conditions":[],"component":"Column","reportComponent":"Column","canRemove":true,"items":[{"key":"3490D5BBB840EFD","reportItemKey":"3490D5BBB840EFD","name":"Paragraph","type":"paragraph","label":"<p style=\"text-align: center;\"><strong>Welcome to the</strong> <strong>Quality Assurance Review tool for EdDiCo!</strong></p>\n<p>This tool has been developed to support the Quality Assurance process designed in the project to select those Open Educational Resources (OER) which will be included in the Catalogue of Learning Opportunities.</p>\n<p>You are invited to complete the Quality review for the resources you are proposing as candidates to be added to the Catalogue and as soon those resources will pass the second Quality review round you will be notified by email.</p>","reportLabel":"","conditions":[],"component":"Paragraph","reportComponent":"Paragraph","canRemove":true,"hidden":false,"hideInForm":false,"class":"","maxWidth":null,"maxWidthUnit":"px"}],"hidden":false,"hideInForm":false,"class":"","maxWidth":null,"maxWidthUnit":"px"}],"hidden":false,"hideInForm":false,"class":"","maxWidth":null,"maxWidthUnit":"px"},{"key":"9BF50CB821228A9","reportItemKey":"9BF50CB821228A9","name":"Row","type":"row","conditions":[],"component":"Row","reportComponent":"Row","canRemove":true,"items":[{"key":"7E0C3C2C1F5359E","reportItemKey":"7E0C3C2C1F5359E","name":"Items holder","type":"column","conditions":[],"component":"Column","reportComponent":"Column","canRemove":true,"items":[{"key":"2ED335796771A34","reportItemKey":"2ED335796771A34","name":"First and last name","type":"first_last_name","defaultValue":null,"label":"Please add your name ","reportLabel":"","conditions":[],"required":false,"canRemove":true,"component":"TextInput","reportComponent":"TextInputReport","hidden":false,"hideInForm":false,"class":"","placeholder":"","maxWidth":null,"maxWidthUnit":"px","includeInAssessmentTitle":false},{"key":"706A4299901B523","reportItemKey":"706A4299901B523","name":"Partner name","type":"select","defaultValue":null,"label":"Partner represented","reportLabel":"","conditions":[],"required":false,"canRemove":true,"component":"SelectInput","reportComponent":"SelectInputReport","options":[{"id":"DHBW","name":"DHBW","score":"0","color":""},{"id":"KIC","name":"KIC","score":"0","color":""},{"id":"VMU","name":"VMU","score":"0","color":""},{"id":"UNIR","name":"UNIR","score":"0","color":""},{"id":"TUNI","name":"TUNI","score":"0","color":""},{"id":"FPM","name":"FPM","score":"0","color":""},{"id":"SV","name":"SV","score":"0","color":""}],"disableForScoring":true,"hidden":false,"hideInForm":false,"class":"","placeholder":"","maxWidth":null,"maxWidthUnit":"px","includeInAssessmentTitle":false,"multiple":false,"scoreGraphColor":""},{"key":"227ACEB8F58B576","reportItemKey":"227ACEB8F58B576","name":"Date input","type":"date","defaultValue":null,"label":"Date of proposing the resource","reportLabel":"","conditions":[],"required":false,"canRemove":true,"component":"DateInput","reportComponent":"DateInputReport","hidden":false,"hideInForm":false,"class":"","placeholder":"","maxWidth":null,"maxWidthUnit":"px"}],"hidden":false,"hideInForm":false,"class":"","maxWidth":null,"maxWidthUnit":"px"}],"hidden":false,"hideInForm":false,"class":"","maxWidth":null,"maxWidthUnit":"px"},{"key":"FA8BFF9BB8A763D","reportItemKey":"FA8BFF9BB8A763D","name":"Row","type":"row","conditions":[],"component":"Row","reportComponent":"Row","canRemove":true,"items":[{"key":"C83637C2357D946","reportItemKey":"C83637C2357D946","name":"Items holder","type":"column","conditions":[],"component":"Column","reportComponent":"Column","canRemove":true,"items":[{"key":"D4265945DF672D9","reportItemKey":"D4265945DF672D9","name":"Assessments","type":"select","defaultValue":null,"label":"Select resource initially reviewed","reportLabel":"","conditions":[],"roleConditions":[],"required":false,"canRemove":true,"component":"AssessmentsInput","reportComponent":"AssessmentsInputReport","options":["author","administrator"],"hidden":false,"hideInForm":false,"class":"","placeholder":"","maxWidth":null,"maxWidthUnit":"px","includeInAssessmentTitle":false,"multiple":false,"queryParameterField":"show_review","disableForScoring":true,"scoreGraphColor":""}],"hidden":false,"hideInForm":false,"class":"","maxWidth":null,"maxWidthUnit":"px"}],"hidden":false,"hideInForm":false,"class":"","maxWidth":null,"maxWidthUnit":"px"},{"key":"456C7F75519FCE0","reportItemKey":"456C7F75519FCE0","name":"Row","type":"row","conditions":[],"component":"Row","reportComponent":"Row","canRemove":true,"items":[{"key":"A35B0AF1329EDC7","reportItemKey":"A35B0AF1329EDC7","name":"Items holder","type":"column","conditions":[],"component":"Column","reportComponent":"Column","canRemove":true,"items":[{"key":"F0025AB0AEB9B90","reportItemKey":"E974615ACB7126D","name":"Name of resource input","type":"textarea","defaultValue":null,"label":"Name of the resource to be reviewed","reportLabel":"","conditions":[],"required":false,"canRemove":true,"component":"TextareaInput","reportComponent":"TextareaInputReport","hidden":false,"hideInForm":false,"class":"","placeholder":"","maxWidth":null,"maxWidthUnit":"px","includeInAssessmentTitle":true},{"key":"A53E1C6505695EE","reportItemKey":"A53E1C6505695EE","name":"Resource_typeSelect input","type":"select","defaultValue":null,"label":"Please select what type of resource are you reviewing","reportLabel":"","conditions":[],"required":false,"canRemove":true,"component":"SelectInput","reportComponent":"SelectInputReport","options":[{"id":"OER","name":"OER","score":"0","color":""},{"id":"Tool","name":"Tool","score":"0","color":""},{"id":"MOOC","name":"MOOC","score":"0","color":""}],"disableForScoring":true,"hidden":false,"hideInForm":false,"class":"","placeholder":"","maxWidth":null,"maxWidthUnit":"px","includeInAssessmentTitle":false,"multiple":false,"scoreGraphColor":""},{"key":"C949BED82881C1B","reportItemKey":"C949BED82881C1B","name":"Resource url input","type":"text","defaultValue":null,"label":"Please add the resource URL (link)","reportLabel":"","conditions":[],"required":false,"canRemove":true,"component":"TextInput","reportComponent":"TextInputReport","hidden":false,"hideInForm":false,"class":"","placeholder":"","maxWidth":null,"maxWidthUnit":"px","includeInAssessmentTitle":false,"isUrl":true},{"key":"F159E31C12E5D79","reportItemKey":"F159E31C12E5D79","name":"Language input","type":"select","defaultValue":null,"label":"Select the resource language","reportLabel":"","conditions":[],"required":false,"canRemove":true,"component":"SelectInput","reportComponent":"SelectInputReport","options":[{"id":"English","name":"English","score":"0","color":""},{"id":"Spanish","name":"Spanish","score":"0","color":""},{"id":"Italian","name":"Italian","score":"0","color":""},{"id":"Finish","name":"Finish","score":"0","color":""},{"id":"French","name":"French","score":"0","color":""},{"id":"German","name":"German","score":"0","color":""},{"id":"Lithuanian","name":"Lithuanian","score":"0","color":""}],"disableForScoring":true,"hidden":false,"hideInForm":false,"class":"","placeholder":"","maxWidth":null,"maxWidthUnit":"px","includeInAssessmentTitle":false,"multiple":false,"scoreGraphColor":""}],"hidden":false,"hideInForm":false,"class":"","maxWidth":null,"maxWidthUnit":"px"}],"hidden":false,"hideInForm":false,"class":"","maxWidth":null,"maxWidthUnit":"px"},{"key":"01FB972FB51BB87","reportItemKey":"01FB972FB51BB87","name":"Row","type":"row","conditions":[],"component":"Row","reportComponent":"Row","canRemove":true,"items":[{"key":"DBC4FDA8935EF92","reportItemKey":"DBC4FDA8935EF92","name":"Items holder","type":"column","conditions":[],"component":"Column","reportComponent":"Column","canRemove":true,"items":[{"key":"18F750315BEFDE3","reportItemKey":"18F750315BEFDE3","name":"Quality criteria set 1 Radio grid input","type":"radio_grid","defaultValue":null,"label":"1.Please assess each of the following aspects related to Licensing criterium","reportLabel":"","conditions":[],"required":true,"canRemove":true,"component":"RadioGridInput","reportComponent":"RadioGridInputReport","optionsHorizontal":[{"id":"1.1 Clear copyright and licensing status","name":"1.1 Clear copyright and licensing status"},{"id":"1.2  License to remix and share available","name":"1.2  License to remix and share available"},{"id":"1.3 Permission to use copyrighted material obtained","name":"1.3 Permission to use copyrighted material obtained"}],"optionsVertical":[{"id":"Yes","name":"Yes","score":"4","color":"#1FBC9C","icon":"dashicons-dashboard"},{"id":"No","name":"No","score":"0","color":"#E84B3C","icon":"dashicons-dashboard"},{"id":"N/A","name":"N/A","score":"1","color":"#F2C511","icon":"dashicons-dashboard"}],"disableForScoring":false,"hidden":false,"hideInForm":false,"class":"","selectedGraph":[{"label":"Pie","key":"pie"}],"maxWidth":null,"maxWidthUnit":"px","scoreGraphColor":null}],"hidden":false,"hideInForm":false,"class":"","maxWidth":null,"maxWidthUnit":"px"}],"hidden":false,"hideInForm":false,"class":"","maxWidth":null,"maxWidthUnit":"px"},{"key":"60556BDCB45C606","reportItemKey":"60556BDCB45C606","name":"Row","type":"row","conditions":[],"component":"Row","reportComponent":"Row","canRemove":true,"items":[{"key":"EC55849477421DF","reportItemKey":"EC55849477421DF","name":"Items holder","type":"column","conditions":[],"component":"Column","reportComponent":"Column","canRemove":true,"items":[{"key":"B39A0E8AE52CFA9","reportItemKey":"B39A0E8AE52CFA9","name":"Set1_Comments for criterium Copyright and licensing statusTextarea input","type":"textarea","defaultValue":null,"label":"Please add your comments for the criterium Copyright and licensing status","reportLabel":"","conditions":[{"field":"18F750315BEFDE3","question":"1.1 Clear copyright and licensing status","selectedOptions":[{"id":"No","name":"No","score":"0","color":"#E84B3C","icon":"dashicons-dashboard"},{"id":"N/A","name":"N/A","score":"0","color":"#F2C511","icon":"dashicons-dashboard"},{"id":"Yes","name":"Yes","score":"4","color":"#1FBC9C","icon":"dashicons-dashboard"}],"value":null}],"required":false,"canRemove":true,"component":"TextareaInput","reportComponent":"TextareaInputReport","hidden":false,"hideInForm":false,"class":"","placeholder":"","maxWidth":null,"maxWidthUnit":"px","includeInAssessmentTitle":false}],"hidden":false,"hideInForm":false,"class":"","maxWidth":null,"maxWidthUnit":"px"}],"hidden":false,"hideInForm":false,"class":"","maxWidth":null,"maxWidthUnit":"px"},{"key":"AA13D634F4D5DBD","reportItemKey":"AA13D634F4D5DBD","name":"Row","type":"row","conditions":[],"component":"Row","reportComponent":"Row","canRemove":true,"items":[{"key":"5F39717CFDAFF93","reportItemKey":"5F39717CFDAFF93","name":"Items holder","type":"column","conditions":[],"component":"Column","reportComponent":"Column","canRemove":true,"items":[{"key":"FA6BED6336D9D5E","reportItemKey":"FA6BED6336D9D5E","name":"Set1_Comments for  license to remix and share availability Textarea input","type":"textarea","defaultValue":null,"label":" Please add your comments for the criterium License to remix and share availability","reportLabel":"","conditions":[{"field":"18F750315BEFDE3","question":"1.2  License to remix and share available","selectedOptions":[{"id":"No","name":"No","score":"0","color":"#E84B3C","icon":"dashicons-dashboard"},{"id":"N/A","name":"N/A","score":"0","color":"#F2C511","icon":"dashicons-dashboard"}],"value":null}],"required":false,"canRemove":true,"component":"TextareaInput","reportComponent":"TextareaInputReport","hidden":false,"hideInForm":false,"class":"","placeholder":"","maxWidth":null,"maxWidthUnit":"px"}],"hidden":false,"hideInForm":false,"class":"","maxWidth":null,"maxWidthUnit":"px"}],"hidden":false,"hideInForm":false,"class":"","maxWidth":null,"maxWidthUnit":"px"},{"key":"28F61D6E638770A","reportItemKey":"28F61D6E638770A","name":"Row","type":"row","conditions":[],"component":"Row","reportComponent":"Row","canRemove":true,"items":[{"key":"346B4CA717CC0C1","reportItemKey":"346B4CA717CC0C1","name":"Items holder","type":"column","conditions":[],"component":"Column","reportComponent":"Column","canRemove":true,"items":[{"key":"31EB7A8681B3D52","reportItemKey":"31EB7A8681B3D52","name":"Set1_Permission to use copyrighted material obtained_Textarea input","type":"textarea","defaultValue":null,"label":" Please add your comments for the criterium Permission to use copyrighted material obtained","reportLabel":"","conditions":[{"field":"18F750315BEFDE3","question":"1.3 Permission to use copyrighted material obtained","selectedOptions":[{"id":"No","name":"No","score":"0","color":"#E84B3C","icon":"dashicons-dashboard"},{"id":"N/A","name":"N/A","score":"0","color":"#F2C511","icon":"dashicons-dashboard"}],"value":null}],"required":false,"canRemove":true,"component":"TextareaInput","reportComponent":"TextareaInputReport","hidden":false,"hideInForm":false,"class":"","placeholder":"","maxWidth":null,"maxWidthUnit":"px"}],"hidden":false,"hideInForm":false,"class":"","maxWidth":null,"maxWidthUnit":"px"}],"hidden":false,"hideInForm":false,"class":"","maxWidth":null,"maxWidthUnit":"px"}],"class":"","nextButtonText":"","previousButtonText":"","hidden":false,"hideInForm":false,"excludeForScoreComparing":false,"showTitle":false,"maxWidth":null,"maxWidthUnit":"px"},{"key":"15F923B884F7026","reportItemKey":"15F923B884F7026","name":"Page 1","type":"page","conditions":[],"component":"Page","reportComponent":"Page","canRemove":true,"items":[{"key":"2F92D14DF970572","reportItemKey":"2F92D14DF970572","name":"Row","type":"row","conditions":[],"component":"Row","reportComponent":"Row","canRemove":true,"items":[{"key":"45E17E3CB9CD410","reportItemKey":"45E17E3CB9CD410","name":"Items holder","type":"column","conditions":[],"component":"Column","reportComponent":"Column","canRemove":true,"items":[{"key":"0D14B16A6B9EFED","reportItemKey":"0D14B16A6B9EFED","name":"Quality criteria set 2 Radio grid input","type":"radio_grid","defaultValue":null,"label":"2. Please assess each of the following aspects related to Accessibility criterium","reportLabel":"","conditions":[],"required":false,"canRemove":true,"component":"RadioGridInput","reportComponent":"RadioGridInputReport","optionsHorizontal":[{"id":"2.1 Accessibility to people with disabilities","name":"2.1 Accessibility to people with disabilities"},{"id":"2.2 Technical problems (wrong links, programming errors)","name":"2.2 Technical problems (wrong links, programming errors)"}],"optionsVertical":[{"id":"Yes","name":"Yes","score":"5","color":"#1FBC9C","icon":"dashicons-dashboard"},{"id":"No","name":"No","score":"0","color":"#E84B3C","icon":"dashicons-dashboard"},{"id":"N/A","name":"N/A","score":"1","color":"#F2C511","icon":"dashicons-dashboard"}],"disableForScoring":false,"hidden":false,"hideInForm":false,"class":"","selectedGraph":[{"label":"Pie","key":"pie"}],"maxWidth":null,"maxWidthUnit":"px","scoreGraphColor":null}],"hidden":false,"hideInForm":false,"class":"","maxWidth":null,"maxWidthUnit":"px"}],"hidden":false,"hideInForm":false,"class":"","maxWidth":null,"maxWidthUnit":"px"},{"key":"584EC3559E70E46","reportItemKey":"584EC3559E70E46","name":"Row","type":"row","conditions":[],"component":"Row","reportComponent":"Row","canRemove":true,"items":[{"key":"DA3C977D8988B89","reportItemKey":"DA3C977D8988B89","name":"Items holder","type":"column","conditions":[],"component":"Column","reportComponent":"Column","canRemove":true,"items":[{"key":"2DD9323459225B8","reportItemKey":"2DD9323459225B8","name":"Set 2_ Comments for Accessibility to people with disabilities_Textarea input","type":"textarea","defaultValue":null,"label":" Please add your comments for the criterium Accessibility to people with disabilities","reportLabel":"","conditions":[{"field":"0D14B16A6B9EFED","question":"2.1 Accessibility to people with disabilities","selectedOptions":[{"id":"No","name":"No","score":"0","color":"#E84B3C","icon":"dashicons-dashboard"},{"id":"N/A","name":"N/A","score":"0","color":"#F2C511","icon":"dashicons-dashboard"}],"value":null}],"required":false,"canRemove":true,"component":"TextareaInput","reportComponent":"TextareaInputReport","hidden":false,"hideInForm":false,"class":"","placeholder":"","maxWidth":null,"maxWidthUnit":"px"}],"hidden":false,"hideInForm":false,"class":"","maxWidth":null,"maxWidthUnit":"px"}],"hidden":false,"hideInForm":false,"class":"","maxWidth":null,"maxWidthUnit":"px"},{"key":"2164535C03004D5","reportItemKey":"2164535C03004D5","name":"Row","type":"row","conditions":[],"component":"Row","reportComponent":"Row","canRemove":true,"items":[{"key":"AF1CB1B4AC834EA","reportItemKey":"AF1CB1B4AC834EA","name":"Items holder","type":"column","conditions":[],"component":"Column","reportComponent":"Column","canRemove":true,"items":[{"key":"7072F527274B28E","reportItemKey":"7072F527274B28E","name":"Set2_TComments for Technical problems_Textarea input","type":"textarea","defaultValue":null,"label":" Please add your comments for the criterium Technical problems (wrong links, programming errors)","reportLabel":"","conditions":[{"field":"0D14B16A6B9EFED","question":"2.2 Technical problems (wrong links, programming errors)","selectedOptions":[{"id":"Yes","name":"Yes","score":"5","color":"#1FBC9C","icon":"dashicons-dashboard"}],"value":null}],"required":false,"canRemove":true,"component":"TextareaInput","reportComponent":"TextareaInputReport","hidden":false,"hideInForm":false,"class":"","placeholder":"","maxWidth":null,"maxWidthUnit":"px","includeInAssessmentTitle":false}],"hidden":false,"hideInForm":false,"class":"","maxWidth":null,"maxWidthUnit":"px"}],"hidden":false,"hideInForm":false,"class":"","maxWidth":null,"maxWidthUnit":"px"},{"key":"B47365E43CC8B0E","reportItemKey":"B47365E43CC8B0E","name":"Row","type":"row","conditions":[],"component":"Row","reportComponent":"Row","canRemove":true,"items":[{"key":"2D9EEF08B377AB0","reportItemKey":"2D9EEF08B377AB0","name":"Items holder","type":"column","conditions":[],"component":"Column","reportComponent":"Column","canRemove":true,"items":[{"key":"E83FB79B5BCC481","reportItemKey":"E83FB79B5BCC481","name":"Quality criteria set 3 Radio grid input","type":"radio_grid","defaultValue":null,"label":"3. Please assess each of the following aspects related to Method criterium","reportLabel":"","conditions":[{"field":"A53E1C6505695EE","question":null,"selectedOptions":[{"id":"MOOC","name":"MOOC","score":"0","color":""}],"value":null}],"required":false,"canRemove":true,"component":"RadioGridInput","reportComponent":"RadioGridInputReport","optionsHorizontal":[{"id":"3.1 Sound pedagogical approach","name":"3.1 Sound pedagogical approach"},{"id":"3.2 Learning objectives and expected learning outcomes clearly indicated.","name":"3.2 Learning objectives and expected learning outcomes clearly indicated."},{"id":" 3.3 Assessment/certification/credentialing options","name":" 3.3 Assessment/certification/credentialing options"},{"id":"3.4 Relevance of content and activities to the related competence (and level) to be developed and to the identified learning expected outcome","name":"3.4 Relevance of content and activities to the related competence (and level) to be developed and to the identified learning expected outcome"}],"optionsVertical":[{"id":"Yes","name":"Yes","score":"5","color":"#1FBC9C","icon":"dashicons-dashboard"},{"id":"No","name":"No","score":"0","color":"#E84B3C","icon":"dashicons-dashboard"},{"id":"N/A","name":"N/A","score":"1","color":"#F2C511","icon":"dashicons-dashboard"}],"disableForScoring":false,"hidden":false,"hideInForm":false,"class":"","selectedGraph":[{"label":"Pie","key":"pie"}],"maxWidth":null,"maxWidthUnit":"px","scoreGraphColor":null,"minScore":null}],"hidden":false,"hideInForm":false,"class":"","maxWidth":null,"maxWidthUnit":"px"}],"hidden":false,"hideInForm":false,"class":"","maxWidth":null,"maxWidthUnit":"px"},{"key":"5CBD5D8090F80DE","reportItemKey":"5CBD5D8090F80DE","name":"Row","type":"row","conditions":[],"component":"Row","reportComponent":"Row","canRemove":true,"items":[{"key":"25B823ED445536B","reportItemKey":"25B823ED445536B","name":"Items holder","type":"column","conditions":[],"component":"Column","reportComponent":"Column","canRemove":true,"items":[{"key":"C3ADF8F68DE1F2D","reportItemKey":"C3ADF8F68DE1F2D","name":"Set3_Comments for Sound pedagogical approach_Textarea input","type":"textarea","defaultValue":null,"label":" Please add your comments for the criterium Sound pedagogical approach","reportLabel":"","conditions":[{"field":"E83FB79B5BCC481","question":"3.1 Sound pedagogical approach","selectedOptions":[{"id":"No","name":"No","score":"0","color":"#E84B3C","icon":"dashicons-dashboard"},{"id":"N/A","name":"N/A","score":"0","color":"#F2C511","icon":"dashicons-dashboard"}],"value":null}],"required":false,"canRemove":true,"component":"TextareaInput","reportComponent":"TextareaInputReport","hidden":false,"hideInForm":false,"class":"","placeholder":"","maxWidth":null,"maxWidthUnit":"px","includeInAssessmentTitle":false}],"hidden":false,"hideInForm":false,"class":"","maxWidth":null,"maxWidthUnit":"px"}],"hidden":false,"hideInForm":false,"class":"","maxWidth":null,"maxWidthUnit":"px"},{"key":"53ED8E94E8486F7","reportItemKey":"53ED8E94E8486F7","name":"Row","type":"row","conditions":[],"component":"Row","reportComponent":"Row","canRemove":true,"items":[{"key":"32C30AE4014DA0B","reportItemKey":"32C30AE4014DA0B","name":"Items holder","type":"column","conditions":[],"component":"Column","reportComponent":"Column","canRemove":true,"items":[{"key":"A1470F74A71B319","reportItemKey":"A1470F74A71B319","name":"Set3_Comments for  Learning objectives _Textarea input","type":"textarea","defaultValue":null,"label":" Please add your comments for the criterium Learning objectives and expected learning outcomes clearly indicated.","reportLabel":"","conditions":[{"field":"E83FB79B5BCC481","question":"3.2 Learning objectives and expected learning outcomes clearly indicated.","selectedOptions":[{"id":"No","name":"No","score":"0","color":"#E84B3C","icon":"dashicons-dashboard"},{"id":"N/A","name":"N/A","score":"0","color":"#F2C511","icon":"dashicons-dashboard"}],"value":null}],"required":false,"canRemove":true,"component":"TextareaInput","reportComponent":"TextareaInputReport","hidden":false,"hideInForm":false,"class":"","placeholder":"","maxWidth":null,"maxWidthUnit":"px","includeInAssessmentTitle":false}],"hidden":false,"hideInForm":false,"class":"","maxWidth":null,"maxWidthUnit":"px"}],"hidden":false,"hideInForm":false,"class":"","maxWidth":null,"maxWidthUnit":"px"},{"key":"2CF1CDA5F6706FD","reportItemKey":"2CF1CDA5F6706FD","name":"Row","type":"row","conditions":[],"component":"Row","reportComponent":"Row","canRemove":true,"items":[{"key":"4D4BD85176D137E","reportItemKey":"4D4BD85176D137E","name":"Items holder","type":"column","conditions":[],"component":"Column","reportComponent":"Column","canRemove":true,"items":[{"key":"A8C2DB398E2CE57","reportItemKey":"A8C2DB398E2CE57","name":"Set3_Comments for  Assessment/certification/credentialing_Textarea input","type":"textarea","defaultValue":null,"label":" Please add your comments for the criterium Assessment/certification/credentialing options","reportLabel":"","conditions":[{"field":"E83FB79B5BCC481","question":" 3.3 Assessment/certification/credentialing options","selectedOptions":[{"id":"No","name":"No","score":"0","color":"#E84B3C","icon":"dashicons-dashboard"},{"id":"N/A","name":"N/A","score":"0","color":"#F2C511","icon":"dashicons-dashboard"}],"value":null}],"required":false,"canRemove":true,"component":"TextareaInput","reportComponent":"TextareaInputReport","hidden":false,"hideInForm":false,"class":"","placeholder":"","maxWidth":null,"maxWidthUnit":"px","includeInAssessmentTitle":false}],"hidden":false,"hideInForm":false,"class":"","maxWidth":null,"maxWidthUnit":"px"}],"hidden":false,"hideInForm":false,"class":"","maxWidth":null,"maxWidthUnit":"px"},{"key":"60B613845E1819E","reportItemKey":"60B613845E1819E","name":"Row","type":"row","conditions":[],"component":"Row","reportComponent":"Row","canRemove":true,"items":[{"key":"D15C4D53369EA53","reportItemKey":"D15C4D53369EA53","name":"Items holder","type":"column","conditions":[],"component":"Column","reportComponent":"Column","canRemove":true,"items":[{"key":"C8FD8EF7E939470","reportItemKey":"C8FD8EF7E939470","name":"Set3_Comments for Relevance of cotents_Textarea input","type":"textarea","defaultValue":null,"label":" Please add your comments for the criterium Relevance of content and activities to the related competence (and level) to be developed and to the identified learning expected outcome","reportLabel":"","conditions":[{"field":"E83FB79B5BCC481","question":"3.4 Relevance of content and activities to the related competence (and level) to be developed and to the identified learning expected outcome","selectedOptions":[{"id":"No","name":"No","score":"0","color":"#E84B3C","icon":"dashicons-dashboard"},{"id":"N/A","name":"N/A","score":"0","color":"#F2C511","icon":"dashicons-dashboard"},{"id":"Yes","name":"Yes","score":"5","color":"#1FBC9C","icon":"dashicons-dashboard"}],"value":null}],"required":false,"canRemove":true,"component":"TextareaInput","reportComponent":"TextareaInputReport","hidden":false,"hideInForm":false,"class":"","placeholder":"","maxWidth":null,"maxWidthUnit":"px","includeInAssessmentTitle":false}],"hidden":false,"hideInForm":false,"class":"","maxWidth":null,"maxWidthUnit":"px"}],"hidden":false,"hideInForm":false,"class":"","maxWidth":null,"maxWidthUnit":"px"}],"class":"","nextButtonText":"","previousButtonText":"","hidden":false,"hideInForm":false,"excludeForScoreComparing":false,"showTitle":false,"maxWidth":null,"maxWidthUnit":"px"},{"key":"132669A6BE4FFB7","reportItemKey":"132669A6BE4FFB7","name":"Page 2","type":"page","conditions":[],"component":"Page","reportComponent":"Page","canRemove":true,"items":[{"key":"A4E8434454BDCE9","reportItemKey":"859087389EEC153","name":"Row","type":"row","conditions":[],"component":"Row","reportComponent":"Row","canRemove":true,"items":[{"key":"8AFD606ADD6B243","reportItemKey":"8AFD606ADD6B243","name":"Items holder","type":"column","conditions":[],"component":"Column","reportComponent":"Column","canRemove":true,"items":[{"key":"98CD9DE17BEA8D8","reportItemKey":"98CD9DE17BEA8D8","name":"Quality criteria set 4 Radio grid input","type":"radio_grid","defaultValue":null,"label":"4. Please assess each of the following aspects related to Accuracy, quality of contents criterium","reportLabel":"","conditions":[{"field":"A53E1C6505695EE","question":null,"selectedOptions":[{"id":"OER","name":"OER","score":"0","color":""},{"id":"MOOC","name":"MOOC","score":"0","color":""}],"value":null}],"required":false,"canRemove":true,"component":"RadioGridInput","reportComponent":"RadioGridInputReport","optionsHorizontal":[{"id":"4.1 Accurate and appropriate content","name":"4.1 Accurate and appropriate content"},{"id":"4.2  Availability of Reference material ","name":"4.2  Availability of Reference material "},{"id":"4.3 Well Identified and cited sources","name":"4.3 Well Identified and cited sources"}],"optionsVertical":[{"id":"Yes","name":"Yes","score":"5","color":"#1FBC9C","icon":"dashicons-dashboard"},{"id":"No","name":"No","score":"0","color":"#E84B3C","icon":"dashicons-dashboard"},{"id":"N/A","name":"N/A","score":"1","color":"#F2C511","icon":"dashicons-dashboard"}],"disableForScoring":false,"hidden":false,"hideInForm":false,"class":"","selectedGraph":[{"label":"Pie","key":"pie"}],"maxWidth":null,"maxWidthUnit":"px","scoreGraphColor":null,"minScore":null}],"hidden":false,"hideInForm":false,"class":"","maxWidth":null,"maxWidthUnit":"px"}],"hidden":false,"hideInForm":false,"class":"","maxWidth":null,"maxWidthUnit":"px"},{"key":"17899CD0B83AE92","reportItemKey":"17899CD0B83AE92","name":"Row","type":"row","conditions":[],"component":"Row","reportComponent":"Row","canRemove":true,"items":[{"key":"F7A8CB88C47148A","reportItemKey":"F7A8CB88C47148A","name":"Items holder","type":"column","conditions":[],"component":"Column","reportComponent":"Column","canRemove":true,"items":[{"key":"FB909A610C1641A","reportItemKey":"FB909A610C1641A","name":"Set4_Comments for Accurate and appropriate content_Textarea input","type":"textarea","defaultValue":null,"label":" Please add your comments for the criterium Accurate and appropriate content","reportLabel":"","conditions":[{"field":"98CD9DE17BEA8D8","question":"4.1 Accurate and appropriate content","selectedOptions":[{"id":"No","name":"No","score":"0","color":"#E84B3C","icon":"dashicons-dashboard"},{"id":"N/A","name":"N/A","score":"0","color":"#F2C511","icon":"dashicons-dashboard"}],"value":null}],"required":false,"canRemove":true,"component":"TextareaInput","reportComponent":"TextareaInputReport","hidden":false,"hideInForm":false,"class":"","placeholder":"","maxWidth":null,"maxWidthUnit":"px"}],"hidden":false,"hideInForm":false,"class":"","maxWidth":null,"maxWidthUnit":"px"}],"hidden":false,"hideInForm":false,"class":"","maxWidth":null,"maxWidthUnit":"px"},{"key":"4E78C40703EB8D0","reportItemKey":"4E78C40703EB8D0","name":"Row","type":"row","conditions":[],"component":"Row","reportComponent":"Row","canRemove":true,"items":[{"key":"9BC616CA47996ED","reportItemKey":"9BC616CA47996ED","name":"Items holder","type":"column","conditions":[],"component":"Column","reportComponent":"Column","canRemove":true,"items":[{"key":"F2AF0146474878E","reportItemKey":"F2AF0146474878E","name":"Set 4_Comments for  Availability of Reference material Textarea input","type":"textarea","defaultValue":null,"label":" Please add your comments for the criterium Availability of Reference material ","reportLabel":"","conditions":[{"field":"98CD9DE17BEA8D8","question":"4.2  Availability of Reference material ","selectedOptions":[{"id":"No","name":"No","score":"0","color":"#E84B3C","icon":"dashicons-dashboard"},{"id":"N/A","name":"N/A","score":"0","color":"#F2C511","icon":"dashicons-dashboard"}],"value":null}],"required":false,"canRemove":true,"component":"TextareaInput","reportComponent":"TextareaInputReport","hidden":false,"hideInForm":false,"class":"","placeholder":"","maxWidth":null,"maxWidthUnit":"px"}],"hidden":false,"hideInForm":false,"class":"","maxWidth":null,"maxWidthUnit":"px"}],"hidden":false,"hideInForm":false,"class":"","maxWidth":null,"maxWidthUnit":"px"},{"key":"F463B19661ABA45","reportItemKey":"F463B19661ABA45","name":"Row","type":"row","conditions":[],"component":"Row","reportComponent":"Row","canRemove":true,"items":[{"key":"2F6F0C25E699EDF","reportItemKey":"2F6F0C25E699EDF","name":"Items holder","type":"column","conditions":[],"component":"Column","reportComponent":"Column","canRemove":true,"items":[{"key":"2ED22B072B18139","reportItemKey":"2ED22B072B18139","name":"Set4_Comments for Well Identified and cited sources_Textarea input","type":"textarea","defaultValue":null,"label":" Please add your comments for the criterium Well Identified and cited sources","reportLabel":"","conditions":[{"field":"98CD9DE17BEA8D8","question":"4.3 Well Identified and cited sources","selectedOptions":[{"id":"No","name":"No","score":"0","color":"#E84B3C","icon":"dashicons-dashboard"},{"id":"N/A","name":"N/A","score":"0","color":"#F2C511","icon":"dashicons-dashboard"}],"value":null}],"required":false,"canRemove":true,"component":"TextareaInput","reportComponent":"TextareaInputReport","hidden":false,"hideInForm":false,"class":"","placeholder":"","maxWidth":null,"maxWidthUnit":"px"}],"hidden":false,"hideInForm":false,"class":"","maxWidth":null,"maxWidthUnit":"px"}],"hidden":false,"hideInForm":false,"class":"","maxWidth":null,"maxWidthUnit":"px"},{"key":"7F50D495EBF4500","reportItemKey":"7F50D495EBF4500","name":"Row","type":"row","conditions":[],"component":"Row","reportComponent":"Row","canRemove":true,"items":[{"key":"B6078FCE08800FA","reportItemKey":"B6078FCE08800FA","name":"Items holder","type":"column","conditions":[],"component":"Column","reportComponent":"Column","canRemove":true,"items":[{"key":"07824DA4ADE8167","reportItemKey":"07824DA4ADE8167","name":"Quality criteria set 5 Radio grid input","type":"radio_grid","defaultValue":null,"label":"5. Please assess each of the following aspects related to Production quality and usability criterium","reportLabel":"","conditions":[],"required":false,"canRemove":true,"component":"RadioGridInput","reportComponent":"RadioGridInputReport","optionsHorizontal":[{"id":" 5.1 Is the information clear and understandable?","name":" 5.1 Is the information clear and understandable?"},{"id":" 5.2 Clear design and instructions for navigation avalable","name":" 5.2 Clear design and instructions for navigation avalable"},{"id":" 5.3 Working navigation tools","name":" 5.3 Working navigation tools"},{"id":"5.4 Possibility of play, replay, stop and volume control provided by navigation elements","name":"5.4 Possibility of play, replay, stop and volume control provided by navigation elements"}],"optionsVertical":[{"id":"Yes","name":"Yes","score":"4","color":"#1FBC9C","icon":"dashicons-dashboard"},{"id":"No","name":"No","score":"0","color":"#E84B3C","icon":"dashicons-dashboard"},{"id":"N/A","name":"N/A","score":"1","color":"#F2C511","icon":"dashicons-dashboard"}],"disableForScoring":false,"hidden":false,"hideInForm":false,"class":"","selectedGraph":[{"label":"Pie","key":"pie"}],"maxWidth":null,"maxWidthUnit":"px","scoreGraphColor":null}],"hidden":false,"hideInForm":false,"class":"","maxWidth":null,"maxWidthUnit":"px"}],"hidden":false,"hideInForm":false,"class":"","maxWidth":null,"maxWidthUnit":"px"},{"key":"BEDFFEEC51DA7DB","reportItemKey":"BEDFFEEC51DA7DB","name":"Row","type":"row","conditions":[],"component":"Row","reportComponent":"Row","canRemove":true,"items":[{"key":"334EC0733FCCCA0","reportItemKey":"334EC0733FCCCA0","name":"Items holder","type":"column","conditions":[],"component":"Column","reportComponent":"Column","canRemove":true,"items":[{"key":"6F94AF5F60C4A86","reportItemKey":"6F94AF5F60C4A86","name":"Set5_Comments for information clear and understandable_Textarea input","type":"textarea","defaultValue":null,"label":" Please add your comments for the crtierium  Information clear and understandable","reportLabel":"","conditions":[{"field":"07824DA4ADE8167","question":" 5.1 Is the information clear and understandable?","selectedOptions":[{"id":"No","name":"No","score":"0","color":"#E84B3C","icon":"dashicons-dashboard"},{"id":"N/A","name":"N/A","score":"0","color":"#F2C511","icon":"dashicons-dashboard"}],"value":null}],"required":false,"canRemove":true,"component":"TextareaInput","reportComponent":"TextareaInputReport","hidden":false,"hideInForm":false,"class":"","placeholder":"","maxWidth":null,"maxWidthUnit":"px","includeInAssessmentTitle":false}],"hidden":false,"hideInForm":false,"class":"","maxWidth":null,"maxWidthUnit":"px"}],"hidden":false,"hideInForm":false,"class":"","maxWidth":null,"maxWidthUnit":"px"},{"key":"AC1819D2CC0DF6D","reportItemKey":"AC1819D2CC0DF6D","name":"Row","type":"row","conditions":[],"component":"Row","reportComponent":"Row","canRemove":true,"items":[{"key":"2115D71CE88604B","reportItemKey":"2115D71CE88604B","name":"Items holder","type":"column","conditions":[],"component":"Column","reportComponent":"Column","canRemove":true,"items":[{"key":"0756701A4F0FEBF","reportItemKey":"0756701A4F0FEBF","name":"Set5_Comments for clear design_Textarea input","type":"textarea","defaultValue":null,"label":"  Please add your comments for the crtierium Clear design and instructions for navigation avalable","reportLabel":"","conditions":[{"field":"07824DA4ADE8167","question":" 5.2 Clear design and instructions for navigation avalable","selectedOptions":[{"id":"No","name":"No","score":"0","color":"#E84B3C","icon":"dashicons-dashboard"},{"id":"N/A","name":"N/A","score":"0","color":"#F2C511","icon":"dashicons-dashboard"}],"value":null}],"required":false,"canRemove":true,"component":"TextareaInput","reportComponent":"TextareaInputReport","hidden":false,"hideInForm":false,"class":"","placeholder":"","maxWidth":null,"maxWidthUnit":"px","includeInAssessmentTitle":false}],"hidden":false,"hideInForm":false,"class":"","maxWidth":null,"maxWidthUnit":"px"}],"hidden":false,"hideInForm":false,"class":"","maxWidth":null,"maxWidthUnit":"px"},{"key":"1AB038CDD9D383F","reportItemKey":"1AB038CDD9D383F","name":"Row","type":"row","conditions":[],"component":"Row","reportComponent":"Row","canRemove":true,"items":[{"key":"7A693D3482995E3","reportItemKey":"7A693D3482995E3","name":"Items holder","type":"column","conditions":[],"component":"Column","reportComponent":"Column","canRemove":true,"items":[{"key":"EF0AE45FC2EB42E","reportItemKey":"EF0AE45FC2EB42E","name":"Set5_Comments for Working navigation tools_Textarea input","type":"textarea","defaultValue":null,"label":" Please add your comments for the crtierium Working navigation tools","reportLabel":"","conditions":[{"field":"07824DA4ADE8167","question":" 5.3 Working navigation tools","selectedOptions":[{"id":"No","name":"No","score":"0","color":"#E84B3C","icon":"dashicons-dashboard"},{"id":"N/A","name":"N/A","score":"0","color":"#F2C511","icon":"dashicons-dashboard"}],"value":null}],"required":false,"canRemove":true,"component":"TextareaInput","reportComponent":"TextareaInputReport","hidden":false,"hideInForm":false,"class":"","placeholder":"","maxWidth":null,"maxWidthUnit":"px","includeInAssessmentTitle":false}],"hidden":false,"hideInForm":false,"class":"","maxWidth":null,"maxWidthUnit":"px"}],"hidden":false,"hideInForm":false,"class":"","maxWidth":null,"maxWidthUnit":"px"},{"key":"E13C1CE5D317E76","reportItemKey":"E13C1CE5D317E76","name":"Row","type":"row","conditions":[],"component":"Row","reportComponent":"Row","canRemove":true,"items":[{"key":"B7375338EBE327F","reportItemKey":"B7375338EBE327F","name":"Items holder","type":"column","conditions":[],"component":"Column","reportComponent":"Column","canRemove":true,"items":[{"key":"72D320F38A135B4","reportItemKey":"72D320F38A135B4","name":"Set5_Comments for play, replay, stop _Textarea input","type":"textarea","defaultValue":null,"label":" Please add your comments for the crtierium Possibility of play, replay, stop and volume control provided by navigation elements","reportLabel":"","conditions":[{"field":"07824DA4ADE8167","question":"5.4 Possibility of play, replay, stop and volume control provided by navigation elements","selectedOptions":[{"id":"No","name":"No","score":"0","color":"#E84B3C","icon":"dashicons-dashboard"},{"id":"N/A","name":"N/A","score":"0","color":"#F2C511","icon":"dashicons-dashboard"}],"value":null}],"required":false,"canRemove":true,"component":"TextareaInput","reportComponent":"TextareaInputReport","hidden":false,"hideInForm":false,"class":"","placeholder":"","maxWidth":null,"maxWidthUnit":"px","includeInAssessmentTitle":false}],"hidden":false,"hideInForm":false,"class":"","maxWidth":null,"maxWidthUnit":"px"}],"hidden":false,"hideInForm":false,"class":"","maxWidth":null,"maxWidthUnit":"px"}],"class":"","nextButtonText":"","previousButtonText":"","hidden":false,"hideInForm":false,"excludeForScoreComparing":false,"showTitle":false,"maxWidth":null,"maxWidthUnit":"px"},{"key":"D29208310860BDA","reportItemKey":"D29208310860BDA","name":"Page 3","type":"page","conditions":[],"component":"Page","reportComponent":"Page","canRemove":true,"items":[{"key":"274EB25566C5395","reportItemKey":"7D2B35AC6CC9E84","name":"Row","type":"row","conditions":[],"component":"Row","reportComponent":"Row","canRemove":true,"items":[{"key":"19BD2450155EC68","reportItemKey":"19BD2450155EC68","name":"Items holder","type":"column","conditions":[],"component":"Column","reportComponent":"Column","canRemove":true,"items":[{"key":"5516F61F497B156","reportItemKey":"5516F61F497B156","name":"Quality criteria set 6 Radio grid input","type":"radio_grid","defaultValue":null,"label":"6. Please assess each of the following aspects related to Cotent producer reputation criterium","reportLabel":"","conditions":[],"required":false,"canRemove":true,"component":"RadioGridInput","reportComponent":"RadioGridInputReport","optionsHorizontal":[{"id":"6.1 Author name available","name":"6.1 Authors' name available"},{"id":"6.2 Risk of plagiarism or forgery issues","name":"6.2 Risk of plagiarism or forgery issues"}],"optionsVertical":[{"id":"Yes","name":"Yes","score":"5","color":"#1FBC9C","icon":"dashicons-dashboard"},{"id":"No","name":"No","score":"0","color":"#E84B3C","icon":"dashicons-dashboard"},{"id":"N/A","name":"N/A","score":"1","color":"#F2C511","icon":"dashicons-dashboard"}],"disableForScoring":false,"hidden":false,"hideInForm":false,"class":"","selectedGraph":[{"label":"Pie","key":"pie"}],"maxWidth":null,"maxWidthUnit":"px","scoreGraphColor":null}],"hidden":false,"hideInForm":false,"class":"","maxWidth":null,"maxWidthUnit":"px"}],"hidden":false,"hideInForm":false,"class":"","maxWidth":null,"maxWidthUnit":"px"},{"key":"C2110A43E5EC393","reportItemKey":"C2110A43E5EC393","name":"Row","type":"row","conditions":[],"component":"Row","reportComponent":"Row","canRemove":true,"items":[{"key":"774668373CA89AE","reportItemKey":"774668373CA89AE","name":"Items holder","type":"column","conditions":[],"component":"Column","reportComponent":"Column","canRemove":true,"items":[{"key":"95228C4E05779C3","reportItemKey":"95228C4E05779C3","name":"Set6_Comment for Authors name avail_Textarea input","type":"textarea","defaultValue":null,"label":" Please add your comments for the crtierium Authors' name available","reportLabel":"","conditions":[{"field":"5516F61F497B156","question":"6.1 Author name available","selectedOptions":[{"id":"No","name":"No","score":"0","color":"#E84B3C","icon":"dashicons-dashboard"},{"id":"N/A","name":"N/A","score":"0","color":"#F2C511","icon":"dashicons-dashboard"}],"value":null}],"required":false,"canRemove":true,"component":"TextareaInput","reportComponent":"TextareaInputReport","hidden":false,"hideInForm":false,"class":"","placeholder":"","maxWidth":null,"maxWidthUnit":"px","includeInAssessmentTitle":false}],"hidden":false,"hideInForm":false,"class":"","maxWidth":null,"maxWidthUnit":"px"}],"hidden":false,"hideInForm":false,"class":"","maxWidth":null,"maxWidthUnit":"px"},{"key":"0C29D3388F1EF7E","reportItemKey":"0C29D3388F1EF7E","name":"Row","type":"row","conditions":[],"component":"Row","reportComponent":"Row","canRemove":true,"items":[{"key":"B2D9130E6070FDD","reportItemKey":"B2D9130E6070FDD","name":"Items holder","type":"column","conditions":[],"component":"Column","reportComponent":"Column","canRemove":true,"items":[{"key":"594E91FCB7F402C","reportItemKey":"594E91FCB7F402C","name":"Set6_Comment for Risk of plagiarism_Textarea input","type":"textarea","defaultValue":null,"label":" Please add your comments for the crtierium Risk of plagiarism or forgery issues","reportLabel":"","conditions":[{"field":"5516F61F497B156","question":"6.2 Risk of plagiarism or forgery issues","selectedOptions":[{"id":"Yes","name":"Yes","score":"5","color":"#1FBC9C","icon":"dashicons-dashboard"}],"value":null}],"required":false,"canRemove":true,"component":"TextareaInput","reportComponent":"TextareaInputReport","hidden":false,"hideInForm":false,"class":"","placeholder":"","maxWidth":null,"maxWidthUnit":"px","includeInAssessmentTitle":false}],"hidden":false,"hideInForm":false,"class":"","maxWidth":null,"maxWidthUnit":"px"}],"hidden":false,"hideInForm":false,"class":"","maxWidth":null,"maxWidthUnit":"px"}],"class":"","nextButtonText":"","previousButtonText":"","hidden":false,"hideInForm":false,"excludeForScoreComparing":false,"showTitle":false,"maxWidth":null,"maxWidthUnit":"px"}]}